and_gate.v
module and_gate(output out,
                input in1, in2);
    wire A;

  	nand(A, in1, in2);
    nand(out, A, A); // Mesma lógica da porta NOT

endmodule

components_new.v
module dlatch (output reg Q,Qn, 
               input wire C,D);
  
  always @ (C or D)
  	begin
  		if (C==1'b1)
  			begin
  				Q <= D;
  				Qn <= ~D;
  	    	end
  	end
  
endmodule

module dflipflop (output reg Q,Qn, 
                  input wire Clock, Reset, Preset, D);
  
  always @ (posedge Clock or negedge Reset or negedge Preset)
  	begin
	  	if (!Reset)
  			begin
  				Q <= 1'b0;
  				Qn <= 1'b1;
  			end
  		else if (!Preset)
  			begin
  				Q <= 1'b1;
  				Qn <= 1'b0;
  			end
  		else
  			begin
  				Q <= D;
  				Qn <= ~D;
  			end

	end
  
endmodule

or_gate.v
module or_gate(output out,
               input in1, in2);

  wire A, B;

  nand(A, in1, in1); //Invertendo o sinal de in1
  nand(B, in2, in2); //Invertendo o sinal de in2
  
  nand(out, A, B);

endmodule

not_gate.v
module not_gate(output out, input in);
  nand(out, in, in);
endmodule

semaforo_fsm_estrutural.v
`include "and_gate.v"
`include "not_gate.v"
`include "or_gate.v"
`include "components_new.v"

module fsm_estrutural (output wire red, ylw, grn,
                       input wire CAR, timeout, Clock, Reset);

  wire and0_ff1, and1_ff1;
  wire and_ff2, or_ff2, not_ff2;
  wire y1n, y2n;

  // Lógica de entrada para o próximo estado do flip-flop 1
  and_gate AND0 (.out(and0_ff1), .in1(y1n), .in2(y2n));
  and_gate AND1 (.out(and1_ff1), .in1(and0_ff1), .in2(CAR));

  // Lógica de entrada para o próximo estado do flip-flop 2
  not_gate NOT0 (.out(not_ff2), .in(timeout));
  and_gate AND2 (.out(and_ff2), .in1(red), .in2(not_ff2));
  or_gate OR0 (.out(or_ff2), .in1(and_ff2), .in2(ylw));

  // Memoria/flip-flop's
  dflipflop FF1 (.Q(ylw), .Qn(y1n), .Clock(Clock), .Reset(Reset), .Preset(), .D(and1_ff1));
  dflipflop FF2 (.Q(red), .Qn(y2n), .Clock(Clock), .Reset(Reset), .Preset(), .D(or_ff2));

  // Lógica de saída para o grn
  and_gate AND3 (.out(grn), .in1(y1n), .in2(y2n));

endmodule

semaforo_fsm_tb.v
`timescale 1ns/1ps

`include "semaforo_fsm_estrutural.v"

module tb_fsm_estrutural;

  reg CAR;
  reg timeout;
  reg Clock;
  reg Reset;
  wire red, ylw, grn;
  
  fsm_estrutural DUT (.red(red), .ylw(ylw), .grn(grn), .CAR(CAR), .timeout(timeout), .Clock(Clock), .Reset(Reset));
  
  // Geração de clock: período de 10 ns (5 ns high, 5 ns low)
  always #5 Clock = ~Clock;
  
  initial begin
    $dumpfile("fsm_waveform.vcd");
    $dumpvars(0, tb_fsm_estrutural);

    // Inicia com reset ativo (Reset = 0) para definir o estado inicial
    Clock = 1'b0;
    Reset  = 1'b0;
    CAR     = 1'b0;
    timeout = 1'b0;    
    #15;  // Mantém o reset ativo por 15 ns
    
    Reset = 1'b1;  // Libera o reset (Reset sobe para 1), iniciando o FSM em estado definido (verde)
    #10;       // Espera para estabilizar
    
    // Estímulo: transição de verde para amarelo ao detectar carro.
    #20;

    CAR = 1'b1;
    #10;
    CAR = 1'b0;
    #15;
    
    // Estímulo: transição do estado vermelho para verde via timeout.
    timeout = 1'b1;
    #10;
    timeout = 1'b0;
    #20;
    
    $finish;
  end
  
endmodule

fsm_waveform.vcd
$date
	Sat Mar 15 22:21:57 2025
$end
$version
	Icarus Verilog
$end
$timescale
	1ps
$end
$scope module tb_fsm_estrutural $end
$var wire 1 ! ylw $end
$var wire 1 " red $end
$var wire 1 # grn $end
$var reg 1 $ CAR $end
$var reg 1 % Clock $end
$var reg 1 & Reset $end
$var reg 1 ' timeout $end
$scope module DUT $end
$var wire 1 $ CAR $end
$var wire 1 % Clock $end
$var wire 1 & Reset $end
$var wire 1 ' timeout $end
$var wire 1 ! ylw $end
$var wire 1 ( y2n $end
$var wire 1 ) y1n $end
$var wire 1 " red $end
$var wire 1 * or_ff2 $end
$var wire 1 + not_ff2 $end
$var wire 1 # grn $end
$var wire 1 , and_ff2 $end
$var wire 1 - and1_ff1 $end
$var wire 1 . and0_ff1 $end
$scope module AND0 $end
$var wire 1 / A $end
$var wire 1 . out $end
$var wire 1 ( in2 $end
$var wire 1 ) in1 $end
$upscope $end
$scope module AND1 $end
$var wire 1 0 A $end
$var wire 1 . in1 $end
$var wire 1 $ in2 $end
$var wire 1 - out $end
$upscope $end
$scope module AND2 $end
$var wire 1 1 A $end
$var wire 1 , out $end
$var wire 1 + in2 $end
$var wire 1 " in1 $end
$upscope $end
$scope module AND3 $end
$var wire 1 2 A $end
$var wire 1 # out $end
$var wire 1 ( in2 $end
$var wire 1 ) in1 $end
$upscope $end
$scope module FF1 $end
$var wire 1 % Clock $end
$var wire 1 - D $end
$var wire 1 3 Preset $end
$var wire 1 & Reset $end
$var reg 1 ! Q $end
$var reg 1 ) Qn $end
$upscope $end
$scope module FF2 $end
$var wire 1 % Clock $end
$var wire 1 4 Preset $end
$var wire 1 & Reset $end
$var wire 1 * D $end
$var reg 1 " Q $end
$var reg 1 ( Qn $end
$upscope $end
$scope module NOT0 $end
$var wire 1 ' in $end
$var wire 1 + out $end
$upscope $end
$scope module OR0 $end
$var wire 1 5 A $end
$var wire 1 6 B $end
$var wire 1 , in1 $end
$var wire 1 ! in2 $end
$var wire 1 * out $end
$upscope $end
$upscope $end
$upscope $end
$enddefinitions $end
$comment Show the parameter values. $end
$dumpall
$end
#0
$dumpvars
16
15
z4
z3
02
11
10
0/
1.
0-
0,
1+
0*
1)
1(
0'
0&
0%
0$
1#
0"
0!
$end
#5000
1%
#10000
0%
#15000
1%
1&
#20000
0%
#25000
1%
#30000
0%
#35000
1%
#40000
0%
#45000
1-
00
1%
1$
#50000
0%
#55000
0#
0.
1*
12
1/
06
0)
1!
0-
10
1%
0$
#60000
0%
#65000
05
1*
1,
16
01
1)
0!
0(
1"
1%
#70000
0*
15
0,
11
0+
0%
1'
#75000
1#
1.
02
0/
1(
0"
1%
#80000
1+
0%
0'
